cidr_trie/__init__.py
cidr_trie/bits_util.py
cidr_trie/cidr_util.py
cidr_trie-3.1.2.dist-info/LICENSE
cidr_trie-3.1.2.dist-info/METADATA
cidr_trie-3.1.2.dist-info/WHEEL
cidr_trie-3.1.2.dist-info/top_level.txt
cidr_trie-3.1.2.dist-info/RECORD
