Metadata-Version: 2.1
Name: cidr-trie
Version: 3.1.2
Summary: Store/search CIDR prefixes in a trie structure.
Home-page: https://github.com/Figglewatts/cidr-trie
Author: Figglewatts
Author-email: me@figglewatts.co.uk
License: MIT
Keywords: cidr ip ipv4 ipv6 trie
Platform: any
Classifier: Development Status :: 5 - Production/Stable
Classifier: Intended Audience :: Developers
Classifier: License :: OSI Approved :: MIT License
Classifier: Programming Language :: Python :: 3 :: Only
Classifier: Topic :: Internet
Classifier: Topic :: Software Development :: Libraries :: Python Modules
